{
	"name": "p_MSD-CDI-CRM_PLAT_DYN_DIVORCECLAIM_STG",
	"properties": {
		"description": "Name - Nikita Varnwal\nDate - June 2023\nProject - CRM Migration, implemented under CHG######\nDescription - This pipeline will pull all the data from the required fields of Asc_Divorceclaim table on a truncate and reload strategy from CRM and load it into CRM_PLAT_DYN_DIVORCECLAIM_STG table in MsDynamics STAGE_CDI. ",
		"activities": [
			{
				"name": "sp-truncate-CRM_PLAT_DYN_DIVORCECLAIM_STG",
				"description": "Name - Nikita Varnwal\nDate - June 2023\nProject - CRM Mirgation, implemented under CHG#####\nDescription - As a part of truncate and reload strategy ,this stored procedure will truncate the table CRM_PLAT_DYN_DIVORCECLAIM_STG before loading any data into it .",
				"type": "SqlServerStoredProcedure",
				"dependsOn": [],
				"policy": {
					"timeout": "0.12:00:00",
					"retry": 0,
					"retryIntervalInSeconds": 30,
					"secureOutput": false,
					"secureInput": false
				},
				"userProperties": [],
				"typeProperties": {
					"storedProcedureName": "[STAGE_CDI].[PRC_TRUNCATE_NAMED_TABLE]",
					"storedProcedureParameters": {
						"p_table_name": {
							"value": {
								"value": "CRM_PLAT_DYN_DIVORCECLAIM_STG",
								"type": "Expression"
							},
							"type": "String"
						}
					}
				},
				"linkedServiceName": {
					"referenceName": "ls_AzureSQLDB",
					"type": "LinkedServiceReference",
					"parameters": {
						"ENVIRONMENT": {
							"value": "@pipeline().globalParameters.ENVIRONMENT",
							"type": "Expression"
						},
						"SHORT_LOCATION": {
							"value": "@pipeline().globalParameters.SHORT_LOCATION",
							"type": "Expression"
						},
						"LOGICAL_ENVIRONMENT": {
							"value": "@pipeline().globalParameters.LOGICAL_ENVIRONMENT",
							"type": "Expression"
						}
					}
				}
			},
			{
				"name": "cd-CRM_PLAT_DYN_DIVORCECLAIM_STG",
				"description": "Name - Nikita Varnwal\nDate - June 2023\nProject - CRM Migration, implemented under CHG######\nDescription - This copy activity will copy all the selected field's data from Asc_DivorceClaim table from CRM to CRM_PLAT_DYN_DIVORCECLAIM_STG table of STAGE_CDI CRM_PLAT_DYN_DIVORCECLAIM_STG table. ",
				"type": "Copy",
				"dependsOn": [
					{
						"activity": "sp-truncate-CRM_PLAT_DYN_DIVORCECLAIM_STG",
						"dependencyConditions": [
							"Succeeded"
						]
					}
				],
				"policy": {
					"timeout": "0.12:00:00",
					"retry": 0,
					"retryIntervalInSeconds": 30,
					"secureOutput": false,
					"secureInput": false
				},
				"userProperties": [],
				"typeProperties": {
					"source": {
						"type": "SqlServerSource",
						"sqlReaderQuery": "SELECT \r\nACTIVITYID\r\n,PRIORITYCODE\r\n,SCHEDULEDEND\r\n,STATECODE\r\n,OWNERID\r\n,OWNERIDNAME\r\n,SUBJECT\r\n,REGARDINGOBJECTID\r\n,ASC_CASETYPE\r\n,ASC_IFAFIRM\r\n,ASC_REGISTEREDIFA\r\n,ASC_BROKER\r\n,ASC_CLIENTMASTER\r\n,ACTUALSTART\r\n,MODIFIEDON\r\n,ASC_DURATION\r\n,CREATEDBY\r\n,CREATEDBYNAME\r\n,ASC_COMPLETEDBY_DRNAME\r\n,ASC_COMPLETEDBY_SETTLEMENTNAME\r\n,ASC_CHECKEDBYNAME\r\n,ASC_COMPLETEDBYNAME\r\n,ASC_CHECKEDBY\r\n,ASC_COMPLETEDBY\r\n,ASC_COMPLETEDBY_DR\r\n,ASC_COMPLETEDBY_SETTLEMENT\r\n,ASC_ADVISERREQUESTEDTOPLACESALES\r\n,ASC_AMOUNTDUE\r\n,ASC_DATECOMPLETED\r\n,ASC_DATENOTIFIED\r\n,ASC_DATEPROCESSED\r\n,ASC_DATEPROCESSED_DR\r\n,ASC_DATEPROCESSED_SETTLEMENT\r\n,ASC_DATERECEIVED\r\n,ASC_DATEUSEDFORPSO\r\n,ASC_DECREEABSOLUTERECEIVED\r\n,ASC_EXTERNALPAYMENTRAISED\r\n,ASC_FEESDEDUCTED\r\n,ASC_INTERNALBALANCETRANSFERRED\r\n,ASC_PENSIONENQUIRYFORMRECEIVED\r\n,ASC_PENSIONSHARINGANNEX\r\n,ASC_PENSIONSHARINGORDERRECEIVED\r\n,ASC_PERCENTAGEOFACCOUNT\r\n,ASC_RECEIVINGSCHEME\r\n,ASC_RELEVANTDOCUMENTSRECEIVED\r\n,ASC_REQUIREMENTLETTEREMAILISSUED\r\n,ASC_WHONOTIFIEDUS\r\n,ASC_REFERENCE\r\n,ASC_CLIENTMASTERNAME\r\n,REGARDINGOBJECTIDNAME\r\nFROM ASC_DIVORCECLAIM\r\n",
						"queryTimeout": "02:00:00",
						"partitionOption": "None"
					},
					"sink": {
						"type": "AzureSqlSink",
						"writeBehavior": "insert",
						"sqlWriterUseTableLock": false
					},
					"enableStaging": false,
					"translator": {
						"type": "TabularTranslator",
						"mappings": [
							{
								"source": {
									"name": "ACTIVITYID",
									"type": "Guid",
									"physicalType": "uniqueidentifier"
								},
								"sink": {
									"name": "ACTIVITYID",
									"type": "String",
									"physicalType": "varchar"
								}
							},
							{
								"source": {
									"name": "PRIORITYCODE",
									"type": "Int32",
									"physicalType": "int"
								},
								"sink": {
									"name": "prioritycode",
									"type": "Decimal",
									"physicalType": "decimal",
									"scale": 0,
									"precision": 10
								}
							},
							{
								"source": {
									"name": "SCHEDULEDEND",
									"type": "DateTime",
									"physicalType": "datetime"
								},
								"sink": {
									"name": "scheduledend",
									"type": "DateTime",
									"physicalType": "datetime2"
								}
							},
							{
								"source": {
									"name": "STATECODE",
									"type": "Int32",
									"physicalType": "int"
								},
								"sink": {
									"name": "statecode",
									"type": "Decimal",
									"physicalType": "decimal",
									"scale": 0,
									"precision": 10
								}
							},
							{
								"source": {
									"name": "OWNERID",
									"type": "Guid",
									"physicalType": "uniqueidentifier"
								},
								"sink": {
									"name": "ownerid",
									"type": "String",
									"physicalType": "varchar"
								}
							},
							{
								"source": {
									"name": "OWNERIDNAME",
									"type": "String",
									"physicalType": "nvarchar"
								},
								"sink": {
									"name": "owneridname",
									"type": "String",
									"physicalType": "varchar"
								}
							},
							{
								"source": {
									"name": "SUBJECT",
									"type": "String",
									"physicalType": "nvarchar"
								},
								"sink": {
									"name": "subject",
									"type": "String",
									"physicalType": "varchar"
								}
							},
							{
								"source": {
									"name": "REGARDINGOBJECTID",
									"type": "Guid",
									"physicalType": "uniqueidentifier"
								},
								"sink": {
									"name": "regardingobjectid",
									"type": "String",
									"physicalType": "varchar"
								}
							},
							{
								"source": {
									"name": "ASC_CASETYPE",
									"type": "Int32",
									"physicalType": "int"
								},
								"sink": {
									"name": "asc_casetype",
									"type": "Decimal",
									"physicalType": "decimal",
									"scale": 0,
									"precision": 10
								}
							},
							{
								"source": {
									"name": "ASC_IFAFIRM",
									"type": "Guid",
									"physicalType": "uniqueidentifier"
								},
								"sink": {
									"name": "asc_ifafirm",
									"type": "String",
									"physicalType": "varchar"
								}
							},
							{
								"source": {
									"name": "ASC_REGISTEREDIFA",
									"type": "Guid",
									"physicalType": "uniqueidentifier"
								},
								"sink": {
									"name": "asc_registeredifa",
									"type": "String",
									"physicalType": "varchar"
								}
							},
							{
								"source": {
									"name": "ASC_BROKER",
									"type": "Guid",
									"physicalType": "uniqueidentifier"
								},
								"sink": {
									"name": "asc_broker",
									"type": "String",
									"physicalType": "varchar"
								}
							},
							{
								"source": {
									"name": "ASC_CLIENTMASTER",
									"type": "Guid",
									"physicalType": "uniqueidentifier"
								},
								"sink": {
									"name": "asc_clientmaster",
									"type": "String",
									"physicalType": "varchar"
								}
							},
							{
								"source": {
									"name": "ACTUALSTART",
									"type": "DateTime",
									"physicalType": "datetime"
								},
								"sink": {
									"name": "actualstart",
									"type": "DateTime",
									"physicalType": "datetime2"
								}
							},
							{
								"source": {
									"name": "MODIFIEDON",
									"type": "DateTime",
									"physicalType": "datetime"
								},
								"sink": {
									"name": "modifiedon",
									"type": "DateTime",
									"physicalType": "datetime2"
								}
							},
							{
								"source": {
									"name": "ASC_DURATION",
									"type": "String",
									"physicalType": "nvarchar"
								},
								"sink": {
									"name": "asc_duration",
									"type": "String",
									"physicalType": "varchar"
								}
							},
							{
								"source": {
									"name": "CREATEDBY",
									"type": "Guid",
									"physicalType": "uniqueidentifier"
								},
								"sink": {
									"name": "createdby",
									"type": "String",
									"physicalType": "varchar"
								}
							},
							{
								"source": {
									"name": "CREATEDBYNAME",
									"type": "String",
									"physicalType": "nvarchar"
								},
								"sink": {
									"name": "createdbyname",
									"type": "String",
									"physicalType": "varchar"
								}
							},
							{
								"source": {
									"name": "ASC_COMPLETEDBY_DRNAME",
									"type": "String",
									"physicalType": "nvarchar"
								},
								"sink": {
									"name": "asc_CompletedBy_DRName",
									"type": "String",
									"physicalType": "varchar"
								}
							},
							{
								"source": {
									"name": "ASC_COMPLETEDBY_SETTLEMENTNAME",
									"type": "String",
									"physicalType": "nvarchar"
								},
								"sink": {
									"name": "asc_CompletedBy_SettlementName",
									"type": "String",
									"physicalType": "varchar"
								}
							},
							{
								"source": {
									"name": "ASC_CHECKEDBYNAME",
									"type": "String",
									"physicalType": "nvarchar"
								},
								"sink": {
									"name": "asc_CheckedByName",
									"type": "String",
									"physicalType": "varchar"
								}
							},
							{
								"source": {
									"name": "ASC_COMPLETEDBYNAME",
									"type": "String",
									"physicalType": "nvarchar"
								},
								"sink": {
									"name": "asc_CompletedByName",
									"type": "String",
									"physicalType": "varchar"
								}
							},
							{
								"source": {
									"name": "ASC_CHECKEDBY",
									"type": "Guid",
									"physicalType": "uniqueidentifier"
								},
								"sink": {
									"name": "asc_CheckedBy",
									"type": "String",
									"physicalType": "varchar"
								}
							},
							{
								"source": {
									"name": "ASC_COMPLETEDBY",
									"type": "Guid",
									"physicalType": "uniqueidentifier"
								},
								"sink": {
									"name": "asc_CompletedBy",
									"type": "String",
									"physicalType": "varchar"
								}
							},
							{
								"source": {
									"name": "ASC_COMPLETEDBY_DR",
									"type": "Guid",
									"physicalType": "uniqueidentifier"
								},
								"sink": {
									"name": "asc_CompletedBy_DR",
									"type": "String",
									"physicalType": "varchar"
								}
							},
							{
								"source": {
									"name": "ASC_COMPLETEDBY_SETTLEMENT",
									"type": "Guid",
									"physicalType": "uniqueidentifier"
								},
								"sink": {
									"name": "asc_CompletedBy_Settlement",
									"type": "String",
									"physicalType": "varchar"
								}
							},
							{
								"source": {
									"name": "ASC_ADVISERREQUESTEDTOPLACESALES",
									"type": "Boolean",
									"physicalType": "bit"
								},
								"sink": {
									"name": "asc_AdviserRequestedtoplaceSales",
									"type": "Decimal",
									"physicalType": "decimal",
									"scale": 0,
									"precision": 1
								}
							},
							{
								"source": {
									"name": "ASC_AMOUNTDUE",
									"type": "Decimal",
									"physicalType": "money",
									"scale": 4,
									"precision": 19
								},
								"sink": {
									"name": "asc_AmountDue",
									"type": "Decimal",
									"physicalType": "decimal",
									"scale": 4,
									"precision": 19
								}
							},
							{
								"source": {
									"name": "ASC_DATECOMPLETED",
									"type": "DateTime",
									"physicalType": "datetime"
								},
								"sink": {
									"name": "asc_DateCompleted",
									"type": "DateTime",
									"physicalType": "datetime2"
								}
							},
							{
								"source": {
									"name": "ASC_DATENOTIFIED",
									"type": "DateTime",
									"physicalType": "datetime"
								},
								"sink": {
									"name": "asc_DateNotified",
									"type": "DateTime",
									"physicalType": "datetime2"
								}
							},
							{
								"source": {
									"name": "ASC_DATEPROCESSED",
									"type": "DateTime",
									"physicalType": "datetime"
								},
								"sink": {
									"name": "asc_DateProcessed",
									"type": "DateTime",
									"physicalType": "datetime2"
								}
							},
							{
								"source": {
									"name": "ASC_DATEPROCESSED_DR",
									"type": "DateTime",
									"physicalType": "datetime"
								},
								"sink": {
									"name": "asc_DateProcessed_DR",
									"type": "DateTime",
									"physicalType": "datetime2"
								}
							},
							{
								"source": {
									"name": "ASC_DATEPROCESSED_SETTLEMENT",
									"type": "DateTime",
									"physicalType": "datetime"
								},
								"sink": {
									"name": "asc_DateProcessed_Settlement",
									"type": "DateTime",
									"physicalType": "datetime2"
								}
							},
							{
								"source": {
									"name": "ASC_DATERECEIVED",
									"type": "DateTime",
									"physicalType": "datetime"
								},
								"sink": {
									"name": "asc_DateReceived",
									"type": "DateTime",
									"physicalType": "datetime2"
								}
							},
							{
								"source": {
									"name": "ASC_DATEUSEDFORPSO",
									"type": "DateTime",
									"physicalType": "datetime"
								},
								"sink": {
									"name": "asc_DateUsedforPSO",
									"type": "DateTime",
									"physicalType": "datetime2"
								}
							},
							{
								"source": {
									"name": "ASC_DECREEABSOLUTERECEIVED",
									"type": "Boolean",
									"physicalType": "bit"
								},
								"sink": {
									"name": "asc_DecreeAbsoluteReceived",
									"type": "Decimal",
									"physicalType": "decimal",
									"scale": 0,
									"precision": 1
								}
							},
							{
								"source": {
									"name": "ASC_EXTERNALPAYMENTRAISED",
									"type": "Boolean",
									"physicalType": "bit"
								},
								"sink": {
									"name": "asc_ExternalPaymentRaised",
									"type": "Decimal",
									"physicalType": "decimal",
									"scale": 0,
									"precision": 1
								}
							},
							{
								"source": {
									"name": "ASC_FEESDEDUCTED",
									"type": "Boolean",
									"physicalType": "bit"
								},
								"sink": {
									"name": "asc_FeesDeducted",
									"type": "Decimal",
									"physicalType": "decimal",
									"scale": 0,
									"precision": 1
								}
							},
							{
								"source": {
									"name": "ASC_INTERNALBALANCETRANSFERRED",
									"type": "Boolean",
									"physicalType": "bit"
								},
								"sink": {
									"name": "asc_InternalBalanceTransferred",
									"type": "Decimal",
									"physicalType": "decimal",
									"scale": 0,
									"precision": 1
								}
							},
							{
								"source": {
									"name": "ASC_PENSIONENQUIRYFORMRECEIVED",
									"type": "Boolean",
									"physicalType": "bit"
								},
								"sink": {
									"name": "asc_PensionEnquiryFormReceived",
									"type": "Decimal",
									"physicalType": "decimal",
									"scale": 0,
									"precision": 1
								}
							},
							{
								"source": {
									"name": "ASC_PENSIONSHARINGANNEX",
									"type": "Boolean",
									"physicalType": "bit"
								},
								"sink": {
									"name": "asc_PensionSharingAnnex",
									"type": "Decimal",
									"physicalType": "decimal",
									"scale": 0,
									"precision": 1
								}
							},
							{
								"source": {
									"name": "ASC_PENSIONSHARINGORDERRECEIVED",
									"type": "Boolean",
									"physicalType": "bit"
								},
								"sink": {
									"name": "asc_PensionSharingOrderReceived",
									"type": "Decimal",
									"physicalType": "decimal",
									"scale": 0,
									"precision": 1
								}
							},
							{
								"source": {
									"name": "ASC_PERCENTAGEOFACCOUNT",
									"type": "Double",
									"physicalType": "float"
								},
								"sink": {
									"name": "asc_PercentageofAccount",
									"type": "Decimal",
									"physicalType": "decimal",
									"scale": 0,
									"precision": 38
								}
							},
							{
								"source": {
									"name": "ASC_RECEIVINGSCHEME",
									"type": "String",
									"physicalType": "nvarchar"
								},
								"sink": {
									"name": "asc_Receivingscheme",
									"type": "String",
									"physicalType": "varchar"
								}
							},
							{
								"source": {
									"name": "ASC_RELEVANTDOCUMENTSRECEIVED",
									"type": "Boolean",
									"physicalType": "bit"
								},
								"sink": {
									"name": "asc_RelevantDocumentsReceived",
									"type": "Decimal",
									"physicalType": "decimal",
									"scale": 0,
									"precision": 1
								}
							},
							{
								"source": {
									"name": "ASC_REQUIREMENTLETTEREMAILISSUED",
									"type": "Boolean",
									"physicalType": "bit"
								},
								"sink": {
									"name": "asc_RequirementLetterEmailIssued",
									"type": "Decimal",
									"physicalType": "decimal",
									"scale": 0,
									"precision": 1
								}
							},
							{
								"source": {
									"name": "ASC_WHONOTIFIEDUS",
									"type": "String",
									"physicalType": "nvarchar"
								},
								"sink": {
									"name": "asc_WhoNotifiedUs",
									"type": "String",
									"physicalType": "varchar"
								}
							},
							{
								"source": {
									"name": "ASC_REFERENCE",
									"type": "String",
									"physicalType": "nvarchar"
								},
								"sink": {
									"name": "ASC_REFERENCE",
									"type": "String",
									"physicalType": "varchar"
								}
							},
							{
								"source": {
									"name": "ASC_CLIENTMASTERNAME",
									"type": "String",
									"physicalType": "nvarchar"
								},
								"sink": {
									"name": "ASC_CLIENTMASTERNAME",
									"type": "String",
									"physicalType": "varchar"
								}
							},
							{
								"source": {
									"name": "REGARDINGOBJECTIDNAME",
									"type": "String",
									"physicalType": "nvarchar"
								},
								"sink": {
									"name": "REGARDINGOBJECTIDNAME",
									"type": "String",
									"physicalType": "varchar"
								}
							}
						],
						"typeConversion": true,
						"typeConversionSettings": {
							"allowDataTruncation": true,
							"treatBooleanAsNumber": true
						}
					}
				},
				"inputs": [
					{
						"referenceName": "ds_MS_DYNAMICS",
						"type": "DatasetReference",
						"parameters": {
							"SCHEMA": "dbo",
							"TABLE_NAME": "Asc_Divorceclaim",
							"ENVIRONMENT": "@pipeline().globalParameters.ENVIRONMENT",
							"LOGICAL_ENVIRONMENT": "@pipeline().globalParameters.LOGICAL_ENVIRONMENT",
							"SHORT_LOCATION": "@pipeline().globalParameters.SHORT_LOCATION"
						}
					}
				],
				"outputs": [
					{
						"referenceName": "ds_ASQLDB_WOKING_SHIR",
						"type": "DatasetReference",
						"parameters": {
							"SCHEMA": "STAGE_CDI",
							"TABLE_NAME": "CRM_PLAT_DYN_DIVORCECLAIM_STG",
							"ENVIRONMENT": "@pipeline().globalParameters.ENVIRONMENT",
							"LOGICAL_ENVIRONMENT": "@pipeline().globalParameters.LOGICAL_ENVIRONMENT",
							"SHORT_LOCATION": "@pipeline().globalParameters.SHORT_LOCATION"
						}
					}
				]
			},
			{
				"name": "sp-UPDATE_BATCH_AUDIT-CRM_PLAT_DYN_DIVORCECLAIM_STG",
				"description": "Name - Nikita Varnwal\nDate - June 2023\nProject - CRM Migration. implemented under CHG#####\nDescription - This stored procedure is updating the BATCH_AUDIT table in STAGE_CDI with the required information of pipeline run .\n",
				"type": "SqlServerStoredProcedure",
				"dependsOn": [
					{
						"activity": "cd-CRM_PLAT_DYN_DIVORCECLAIM_STG",
						"dependencyConditions": [
							"Succeeded"
						]
					}
				],
				"policy": {
					"timeout": "0.12:00:00",
					"retry": 0,
					"retryIntervalInSeconds": 30,
					"secureOutput": false,
					"secureInput": false
				},
				"userProperties": [],
				"typeProperties": {
					"storedProcedureName": "[STAGE_CDI].[PRC_BATCH_AUDIT]",
					"storedProcedureParameters": {
						"p_billable_duration": {
							"value": {
								"value": "@activity('cd-CRM_PLAT_DYN_DIVORCECLAIM_STG').output.billingReference.billableDuration[0].duration",
								"type": "Expression"
							},
							"type": "Decimal"
						},
						"p_billable_unit": {
							"value": {
								"value": "@activity('cd-CRM_PLAT_DYN_DIVORCECLAIM_STG').output.billingReference.billableDuration[0].unit",
								"type": "Expression"
							},
							"type": "String"
						},
						"p_duration": {
							"value": {
								"value": "@activity('cd-CRM_PLAT_DYN_DIVORCECLAIM_STG').output.copyDuration",
								"type": "Expression"
							},
							"type": "Int32"
						},
						"p_pipeline_name": {
							"value": {
								"value": "@pipeline().Pipeline",
								"type": "Expression"
							},
							"type": "String"
						},
						"p_process_start_dt": {
							"value": {
								"value": "@activity('cd-CRM_PLAT_DYN_DIVORCECLAIM_STG').output.executionDetails[0].start",
								"type": "Expression"
							},
							"type": "String"
						},
						"p_records_read": {
							"value": {
								"value": "@activity('cd-CRM_PLAT_DYN_DIVORCECLAIM_STG').output.rowsRead",
								"type": "Expression"
							},
							"type": "Int32"
						},
						"p_records_written": {
							"value": {
								"value": "@activity('cd-CRM_PLAT_DYN_DIVORCECLAIM_STG').output.rowsCopied",
								"type": "Expression"
							},
							"type": "Int32"
						},
						"p_table_name": {
							"value": "CRM_PLAT_DYN_DIVORCECLAIM_STG",
							"type": "String"
						},
						"p_trigger_name": {
							"value": {
								"value": "@pipeline().TriggerName",
								"type": "Expression"
							},
							"type": "String"
						}
					}
				},
				"linkedServiceName": {
					"referenceName": "ls_AzureSQLDB",
					"type": "LinkedServiceReference",
					"parameters": {
						"ENVIRONMENT": {
							"value": "@pipeline().globalParameters.ENVIRONMENT",
							"type": "Expression"
						},
						"SHORT_LOCATION": {
							"value": "@pipeline().globalParameters.SHORT_LOCATION",
							"type": "Expression"
						},
						"LOGICAL_ENVIRONMENT": {
							"value": "@pipeline().globalParameters.LOGICAL_ENVIRONMENT",
							"type": "Expression"
						}
					}
				}
			}
		],
		"folder": {
			"name": "MSDynamics Migration"
		},
		"annotations": []
	}
}