{
	"name": "ds_STAGE_CRM",
	"properties": {
		"description": "Connects to STAGE_CRM (CRM01A)",
		"linkedServiceName": {
			"referenceName": "ls_STAGE_CRM",
			"type": "LinkedServiceReference"
		},
		"parameters": {
			"SCHEMA": {
				"type": "string"
			},
			"TABLE": {
				"type": "string"
			}
		},
		"annotations": [],
		"type": "OracleTable",
		"schema": [],
		"typeProperties": {
			"schema": {
				"value": "@dataset().SCHEMA",
				"type": "Expression"
			},
			"table": {
				"value": "@dataset().TABLE",
				"type": "Expression"
			}
		}
	}
}